streambp/__init__.py
streambp/stream_model.py
streambp/stream_model_gemma.py
streambp/trainers/__init__.py
streambp/trainers/stream_dpo_trainer.py
streambp/trainers/stream_grpo_trainer.py
streambp/trainers/stream_sft_trainer.py
streambp-1.0.dist-info/METADATA
streambp-1.0.dist-info/WHEEL
streambp-1.0.dist-info/top_level.txt
streambp-1.0.dist-info/RECORD
